promethium/__init__.py
promethium/balancer.py
promethium/element_handler.py
promethium/data/alembic_version.csv
promethium/data/elements.csv
promethium/data/groups.csv
promethium/data/ionicradii.csv
promethium/data/ionizationenergies.csv
promethium/data/isotopedecaymodes.csv
promethium/data/isotopes.csv
promethium/data/oxidationstates.csv
promethium/data/phasetransitions.csv
promethium/data/propertymetadata.csv
promethium/data/scattering_factors.csv
promethium/data/screeningconstants.csv
promethium/data/series.csv
promethium_py-1.0.0.dist-info/METADATA
promethium_py-1.0.0.dist-info/WHEEL
promethium_py-1.0.0.dist-info/top_level.txt
promethium_py-1.0.0.dist-info/RECORD
