Metadata-Version: 2.4
Name: promethium-py
Version: 1.0.0
Summary: A Pythonic interface to a rich, offline database of chemical information.
Home-page: https://github.com/rohankishore/promethium
Author: Rohan Kishore
Author-email: rohankishore746@gmail.com
License: MIT
Classifier: Programming Language :: Python :: 3
Classifier: Operating System :: OS Independent
Requires-Python: >=3.8
Requires-Dist: pandas
Requires-Dist: numpy
Dynamic: author
Dynamic: author-email
Dynamic: classifier
Dynamic: description
Dynamic: description-content-type
Dynamic: home-page
Dynamic: license
Dynamic: requires-dist
Dynamic: requires-python
Dynamic: summary
